LICENSE.txt
README.md
setup.py
src/channel_advisor/__init__.py
src/channel_advisor/helper.py
src/ivaluemart_channel_advisor.egg-info/PKG-INFO
src/ivaluemart_channel_advisor.egg-info/SOURCES.txt
src/ivaluemart_channel_advisor.egg-info/dependency_links.txt
src/ivaluemart_channel_advisor.egg-info/top_level.txt
test/test_channel_advisor.py
test/testutil.py