Metadata-Version: 2.1
Name: ivaluemart-channel-advisor
Version: 1.0.0
Summary: UNKNOWN
Home-page: UNKNOWN
Author: ivaluemart
Author-email: shahid@ivaluemart.com
License: LICENSE.txt
Platform: UNKNOWN
License-File: LICENSE.txt
